rsbooster/VERSION
rsbooster/__init__.py
rsbooster/diffmaps/__init__.py
rsbooster/diffmaps/diffmap.py
rsbooster/diffmaps/internaldiffmap.py
rsbooster/diffmaps/weights.py
rsbooster/esf/__init__.py
rsbooster/esf/extrapolate.py
rsbooster/io/__init__.py
rsbooster/io/dials2mtz.py
rsbooster/io/precog2mtz.py
rsbooster/realspace/__init__.py
rsbooster/realspace/find_peaks.py
rsbooster/scaleit/__init__.py
rsbooster/scaleit/scaleit.py
rsbooster/stats/__init__.py
rsbooster/stats/ccanom.py
rsbooster/stats/cchalf.py
rsbooster/stats/ccpred.py
rsbooster/stats/ccsym.py
rsbooster/stats/parser.py
rsbooster/utils/__init__.py
rsbooster/utils/io.py
rsbooster/utils/rfree.py
tests/__init__.py
tests/test_rfree.py
tests/test_rsbooster.py
rs_booster-0.1.3.dist-info/LICENSE
rs_booster-0.1.3.dist-info/METADATA
rs_booster-0.1.3.dist-info/WHEEL
rs_booster-0.1.3.dist-info/entry_points.txt
rs_booster-0.1.3.dist-info/top_level.txt
rs_booster-0.1.3.dist-info/RECORD
